heapMAX/Max Heap.py
heapMAX/__init__.py
heapMAX-0.0.2.dist-info/LICENSE.txt
heapMAX-0.0.2.dist-info/METADATA
heapMAX-0.0.2.dist-info/WHEEL
heapMAX-0.0.2.dist-info/top_level.txt
heapMAX-0.0.2.dist-info/RECORD
